[
    {
        "id":"stoutford_farmer2",
        "name":"Busy farmer",
        "iconID":"monsters_man1:0",
        "monsterClass":"humanoid",
        "spawnGroup":"stoutford_farmer2",
        "phraseID":"stoutford_farmer2"
    },
    {
        "id":"stoutford_farmer3",
        "name":"Old farmer",
        "iconID":"monsters_mage2:0",
        "monsterClass":"humanoid",
        "spawnGroup":"stoutford_farmer3",
        "phraseID":"stoutford_farmer3"
    },
    {
        "id":"stoutford_commoner4",
        "name":"Old woman",
        "iconID":"monsters_ld1:180",
        "monsterClass":"humanoid",
        "spawnGroup":"stoutford_commoner4",
        "phraseID":"stoutford_commoner4"
    },
    {
        "id":"stoutford_armorer",
        "name":"Odirath",
        "iconID":"monsters_ld1:10",
        "monsterClass":"humanoid",
        "spawnGroup":"stoutford_armorer",
        "phraseID":"odirath_0",
        "droplistID":"shop_odirath"
    },
    {
        "id":"cave_troll_1",
        "name":"Cave troll",
        "iconID":"monsters_tometik5:14",
        "maxHP":230,
        "maxAP":10,
        "moveCost":5,
        "monsterClass":"giant",
        "attackDamage":{
            "min":1,
            "max":15
        },
        "spawnGroup":"cave_troll_1",
        "droplistID":"cave_troll_1",
        "attackCost":5,
        "attackChance":60,
        "blockChance":40,
        "hitEffect":{
            "conditionsTarget":[
                {
                    "condition":"stunned",
                    "magnitude":1,
                    "duration":2,
                    "chance":"10"
                }
            ]
        }
    },
    {
        "id":"cave_troll_2",
        "name":"Strong cave troll",
        "iconID":"monsters_tometik5:15",
        "maxHP":250,
        "maxAP":10,
        "moveCost":5,
        "monsterClass":"giant",
        "attackDamage":{
            "min":5,
            "max":15
        },
        "spawnGroup":"cave_troll_2",
        "droplistID":"cave_troll_1",
        "attackCost":5,
        "attackChance":65,
        "blockChance":40,
        "hitEffect":{
            "conditionsTarget":[
                {
                    "condition":"stunned",
                    "magnitude":1,
                    "duration":2,
                    "chance":"15"
                }
            ]
        }
    },
    {
        "id":"cave_troll_3",
        "name":"Tough cave troll",
        "iconID":"monsters_tometik5:16",
        "maxHP":290,
        "maxAP":10,
        "moveCost":5,
        "monsterClass":"giant",
        "attackDamage":{
            "min":5,
            "max":15
        },
        "spawnGroup":"cave_troll_3",
        "droplistID":"cave_troll_1",
        "attackCost":5,
        "attackChance":65,
        "blockChance":50,
        "hitEffect":{
            "conditionsTarget":[
                {
                    "condition":"stunned",
                    "magnitude":1,
                    "duration":2,
                    "chance":"15"
                }
            ]
        }
    },
    {
        "id":"cave_troll_4",
        "name":"Cave troll shaman",
        "iconID":"monsters_tometik5:17",
        "maxHP":300,
        "maxAP":10,
        "moveCost":5,
        "monsterClass":"giant",
        "attackDamage":{
            "min":1,
            "max":15
        },
        "spawnGroup":"cave_troll_4",
        "droplistID":"cave_troll_2",
        "attackCost":5,
        "attackChance":60,
        "blockChance":40,
        "hitEffect":{
            "conditionsTarget":[
                {
                    "condition":"stunned",
                    "magnitude":1,
                    "duration":2,
                    "chance":"15"
                },
                {
                    "condition":"dazed",
                    "magnitude":1,
                    "duration":3,
                    "chance":"10"
                },
                {
                    "condition":"fatigue_minor",
                    "magnitude":1,
                    "duration":4,
                    "chance":"10"
                }
            ]
        }
    },
    {
        "id":"cave_troll_5",
        "name":"Cave troll leader",
        "iconID":"monsters_tometik5:18",
        "maxHP":410,
        "maxAP":10,
        "moveCost":5,
        "unique":1,
        "monsterClass":"giant",
        "attackDamage":{
            "min":5,
            "max":20
        },
        "spawnGroup":"cave_troll_5",
        "phraseID":"lakecave2_troll_10",
        "droplistID":"cave_troll_4",
        "attackCost":5,
        "attackChance":70,
        "blockChance":50,
        "hitEffect":{
            "conditionsSource":[
                {
                    "condition":"stunned",
                    "magnitude":1,
                    "duration":3,
                    "chance":"25"
                }
            ],
            "conditionsTarget":[
                {
                    "condition":"stunned",
                    "magnitude":1,
                    "duration":3,
                    "chance":"25"
                }
            ]
        }
    },
    {
        "id":"lakecave2_key",
        "name":"Glade key",
        "iconID":"items_japozero:387",
        "unique":1,
        "spawnGroup":"lakecave2_key",
        "phraseID":"lakecave2_key_check2"
    },
    {
        "id":"lakecave2_key2",
        "name":"Glade key",
        "iconID":"items_japozero:387",
        "unique":1,
        "spawnGroup":"lakecave2_key2",
        "phraseID":"lakecave2_key_found"
    },
    {
        "id":"cave_scorpion_0",
        "name":"Cave scorpion",
        "iconID":"monsters_tometik3:74",
        "maxHP":30,
        "maxAP":10,
        "moveCost":5,
        "monsterClass":"insect",
        "movementAggressionType":"none",
        "attackDamage":{
            "min":3,
            "max":6
        },
        "spawnGroup":"scorpion_1",
        "droplistID":"cave_scorpion",
        "attackCost":3,
        "attackChance":80,
        "blockChance":100,
        "damageResistance":1,
        "hitEffect":{
            "conditionsTarget":[
                {
                    "condition":"sting_minor",
                    "magnitude":1,
                    "duration":3,
                    "chance":"20"
                }
            ]
        }
    },
    {
        "id":"cave_scorpion_1",
        "name":"Aggressive cave scorpion",
        "iconID":"monsters_tometik3:72",
        "maxHP":35,
        "maxAP":10,
        "moveCost":5,
        "monsterClass":"insect",
        "movementAggressionType":"helpOthers",
        "attackDamage":{
            "min":4,
            "max":7
        },
        "spawnGroup":"scorpion_2",
        "droplistID":"cave_scorpion",
        "attackCost":3,
        "attackChance":100,
        "blockChance":100,
        "damageResistance":1,
        "hitEffect":{
            "conditionsTarget":[
                {
                    "condition":"sting_minor",
                    "magnitude":2,
                    "duration":2,
                    "chance":"20"
                }
            ]
        }
    },
    {
        "id":"cave_scorpion_2",
        "name":"Puny cave scorpion",
        "iconID":"monsters_tometik3:77",
        "maxHP":30,
        "maxAP":10,
        "moveCost":5,
        "monsterClass":"insect",
        "movementAggressionType":"none",
        "attackDamage":{
            "min":2,
            "max":5
        },
        "spawnGroup":"scorpion_1",
        "droplistID":"cave_scorpion",
        "attackCost":3,
        "attackChance":80,
        "blockChance":85,
        "hitEffect":{
            "conditionsTarget":[
                {
                    "condition":"sting_minor",
                    "magnitude":1,
                    "duration":2,
                    "chance":"20"
                }
            ]
        }
    },
    {
        "id":"cave_scorpion_3",
        "name":"Tough cave scorpion",
        "iconID":"monsters_tometik3:76",
        "maxHP":30,
        "maxAP":10,
        "moveCost":5,
        "monsterClass":"insect",
        "movementAggressionType":"helpOthers",
        "attackDamage":{
            "min":3,
            "max":6
        },
        "spawnGroup":"scorpion_2",
        "droplistID":"cave_scorpion",
        "attackCost":3,
        "attackChance":80,
        "blockChance":100,
        "damageResistance":2,
        "hitEffect":{
            "conditionsTarget":[
                {
                    "condition":"sting_minor",
                    "magnitude":2,
                    "duration":2,
                    "chance":"20"
                }
            ]
        }
    },
    {
        "id":"cave_scorpion_4",
        "name":"Armored cave scorpion",
        "iconID":"monsters_tometik3:73",
        "maxHP":35,
        "maxAP":10,
        "moveCost":5,
        "monsterClass":"insect",
        "movementAggressionType":"protectSpawn",
        "attackDamage":{
            "min":4,
            "max":8
        },
        "spawnGroup":"scorpion_3",
        "droplistID":"cave_scorpion",
        "attackCost":3,
        "attackChance":100,
        "blockChance":120,
        "damageResistance":4,
        "hitEffect":{
            "conditionsTarget":[
                {
                    "condition":"sting_minor",
                    "magnitude":2,
                    "duration":3,
                    "chance":"25"
                }
            ]
        }
    },
    {
        "id":"cave_scorpion_5",
        "name":"Fierce cave scorpion",
        "iconID":"monsters_tometik3:75",
        "maxHP":35,
        "maxAP":10,
        "moveCost":5,
        "monsterClass":"insect",
        "movementAggressionType":"protectSpawn",
        "attackDamage":{
            "min":5,
            "max":10
        },
        "spawnGroup":"scorpion_3",
        "droplistID":"cave_scorpion",
        "attackCost":3,
        "attackChance":130,
        "blockChance":100,
        "damageResistance":3,
        "hitEffect":{
            "conditionsTarget":[
                {
                    "condition":"sting_minor",
                    "magnitude":2,
                    "duration":3,
                    "chance":"25"
                }
            ]
        }
    },
    {
        "id":"cave_troll_6",
        "name":"Cave troll shaman",
        "iconID":"monsters_tometik5:17",
        "maxHP":370,
        "maxAP":10,
        "moveCost":5,
        "unique":1,
        "monsterClass":"giant",
        "attackDamage":{
            "min":7,
            "max":18
        },
        "spawnGroup":"cave_troll_6",
        "droplistID":"cave_troll_3",
        "attackCost":5,
        "attackChance":90,
        "blockChance":70,
        "damageResistance":4,
        "hitEffect":{
            "conditionsTarget":[
                {
                    "condition":"stunned",
                    "magnitude":1,
                    "duration":2,
                    "chance":"15"
                },
                {
                    "condition":"dazed",
                    "magnitude":1,
                    "duration":3,
                    "chance":"10"
                },
                {
                    "condition":"fatigue_minor",
                    "magnitude":1,
                    "duration":4,
                    "chance":"10"
                }
            ]
        }
    },
    {
        "id":"honey_bee",
        "name":"Honey bee",
        "iconID":"monsters_tometik10:48",
        "movementAggressionType":"none",
        "spawnGroup":"honey_bee",
        "phraseID":"honey_bee"
    },
    {
        "id":"erwyn_knight",
        "name":"Erwyn's knight",
        "iconID":"monsters_tometik8:41",
        "maxHP":75,
        "unique":1,
        "monsterClass":"undead",
        "movementAggressionType":"protectSpawn",
        "attackDamage":{
            "min":4,
            "max":6
        },
        "spawnGroup":"erwyn_knight",
        "phraseID":"stoutford_castle_0",
        "attackCost":3,
        "attackChance":100,
        "blockChance":70
    },
    {
        "id":"erwyn_soldier",
        "name":"Erwyn's soldier",
        "iconID":"monsters_tometik8:38",
        "maxHP":65,
        "unique":1,
        "monsterClass":"undead",
        "movementAggressionType":"helpOthers",
        "attackDamage":{
            "min":4,
            "max":5
        },
        "spawnGroup":"erwyn_soldier",
        "phraseID":"stoutford_castle_1",
        "attackCost":3,
        "attackChance":90,
        "blockChance":60,
        "damageResistance":0
    },
    {
        "id":"erwyn_soldier2",
        "name":"Erwyn's soldier",
        "iconID":"monsters_tometik8:38",
        "maxHP":65,
        "unique":1,
        "monsterClass":"humanoid",
        "movementAggressionType":"helpOthers",
        "attackDamage":{
            "min":4,
            "max":5
        },
        "spawnGroup":"erwyn_soldier2",
        "phraseID":"stoutford_castle_1b",
        "attackCost":3,
        "attackChance":90,
        "blockChance":60,
        "damageResistance":0
    },
    {
        "id":"erwyn_soldier3",
        "name":"Erwyn's soldier",
        "iconID":"monsters_tometik8:38",
        "maxHP":65,
        "unique":1,
        "monsterClass":"humanoid",
        "movementAggressionType":"helpOthers",
        "attackDamage":{
            "min":4,
            "max":5
        },
        "spawnGroup":"erwyn_soldier3",
        "phraseID":"stoutford_castle_1c",
        "attackCost":3,
        "attackChance":90,
        "blockChance":60,
        "damageResistance":0
    },
    {
        "id":"erwyn_servant",
        "name":"Servant",
        "iconID":"monsters_tometik8:28",
        "maxHP":30,
        "unique":1,
        "monsterClass":"undead",
        "movementAggressionType":"none",
        "attackDamage":{
            "min":1,
            "max":3
        },
        "spawnGroup":"erwyn_servant",
        "attackCost":5,
        "attackChance":50,
        "blockChance":20
    },
    {
        "id":"erwyn_cook",
        "name":"Cook",
        "iconID":"monsters_tometik8:35",
        "maxHP":35,
        "unique":1,
        "monsterClass":"undead",
        "attackDamage":{
            "min":2,
            "max":3
        },
        "spawnGroup":"erwyn_cook",
        "attackCost":5,
        "attackChance":50,
        "blockChance":20
    },
    {
        "id":"erwyn_commander",
        "name":"Karth the Unbowed",
        "iconID":"monsters_tometik8:45",
        "maxHP":90,
        "unique":1,
        "monsterClass":"undead",
        "attackDamage":{
            "min":15,
            "max":23
        },
        "spawnGroup":"erwyn_commander",
        "phraseID":"stoutford_castle_2",
        "attackChance":150,
        "blockChance":75,
        "damageResistance":4
    },
    {
        "id":"flagstone_guard",
        "name":"Guard",
        "iconID":"monsters_tometik2:44",
        "spawnGroup":"flagstone_guard",
        "phraseID":"flagstone_guard"
    },
    {
        "id":"erwyn",
        "name":"Lord Erwyn",
        "iconID":"monsters_tometik8:46",
        "maxHP":110,
        "unique":1,
        "monsterClass":"undead",
        "movementAggressionType":"helpOthers",
        "attackDamage":{
            "min":13,
            "max":22
        },
        "spawnGroup":"erwyn",
        "phraseID":"stoutford_castle_3",
        "attackCost":5,
        "attackChance":130,
        "criticalSkill":20,
        "criticalMultiplier":3.0,
        "blockChance":80,
        "damageResistance":5,
        "hitEffect":{
            "increaseCurrentHP":{
                "min":3,
                "max":3
            },
            "conditionsTarget":[
                {
                    "condition":"poison_weak",
                    "magnitude":2,
                    "duration":4,
                    "chance":"40"
                }
            ]
        }
    },
    {
        "id":"erwyn2",
        "name":"Lord Erwyn",
        "iconID":"monsters_tometik8:46",
        "maxHP":110,
        "unique":1,
        "monsterClass":"undead",
        "movementAggressionType":"helpOthers",
        "attackDamage":{
            "min":13,
            "max":22
        },
        "spawnGroup":"erwyn2",
        "phraseID":"stoutford_castle_3",
        "droplistID":"erwyn",
        "attackCost":5,
        "attackChance":130,
        "criticalSkill":20,
        "criticalMultiplier":3.0,
        "blockChance":80,
        "damageResistance":5,
        "hitEffect":{
            "increaseCurrentHP":{
                "min":3,
                "max":3
            },
            "conditionsTarget":[
                {
                    "condition":"poison_weak",
                    "magnitude":2,
                    "duration":4,
                    "chance":"40"
                }
            ]
        }
    },
    {
        "id":"erwyn_child",
        "name":"Undead child",
        "iconID":"monsters_rltiles4:0",
        "phraseID":"erwyn_child"
    },
    {
        "id":"stoutford_guard1_b",
        "name":"Stoutford guard",
        "iconID":"monsters_tometik2:44",
        "spawnGroup":"stoutford_guard1",
        "phraseID":"stoutford_guard1_0b"
    },
    {
        "id":"stoutford_guard1_c",
        "name":"Stoutford guard",
        "iconID":"monsters_tometik2:44",
        "spawnGroup":"stoutford_guard1",
        "phraseID":"stoutford_guard1_0c"
    },
    {
        "id":"stoutford_guard1a",
        "name":"Stoutford guard",
        "iconID":"monsters_tometik2:44",
        "spawnGroup":"stoutford_guard1a",
        "phraseID":"stoutford_guard1_0"
    },
    {
        "id":"stoutford_guard1b",
        "name":"Stoutford guard",
        "iconID":"monsters_tometik2:44",
        "phraseID":"stoutford_guard1_0"
    },
    {
        "id":"stoutford_guard1c",
        "name":"Stoutford guard",
        "iconID":"monsters_tometik2:44",
        "phraseID":"stoutford_guard1_0"
    },
    {
        "id":"stoutford_guard2",
        "name":"Stoutford guard",
        "iconID":"monsters_tometik2:45",
        "monsterClass":"humanoid",
        "spawnGroup":"stoutford_guard1",
        "phraseID":"stoutford_guard2"
    },
    {
        "id":"stoutford_guard3",
        "name":"Stoutford guard",
        "iconID":"monsters_tometik7:71",
        "monsterClass":"humanoid",
        "spawnGroup":"stoutford_guard1",
        "phraseID":"stoutford_guard3"
    },
    {
        "id":"stoutford_guard4",
        "name":"Stoutford guard",
        "iconID":"monsters_tometik7:71",
        "monsterClass":"humanoid",
        "phraseID":"stoutford_guard4"
    },
    {
        "id":"stoutford_guard_wild21a",
        "name":"Stoutford guard",
        "iconID":"monsters_tometik7:71",
        "monsterClass":"humanoid",
        "phraseID":"key_wild21a"
    },
    {
        "id":"stoutford_guard_camp1",
        "name":"Stoutford guard",
        "iconID":"monsters_tometik7:71",
        "maxHP":40,
        "moveCost":5,
        "unique":1,
        "monsterClass":"humanoid",
        "movementAggressionType":"helpOthers",
        "attackDamage":{
            "min":1,
            "max":6
        },
        "spawnGroup":"stoutford_guard_camp",
        "faction":"stoutford_guard_camp",
        "phraseID":"stoutford_guard_camp1_10",
        "attackCost":5,
        "attackChance":50,
        "blockChance":100
    },
    {
        "id":"stoutford_guard_camp2",
        "name":"Stoutford guard",
        "iconID":"monsters_tometik7:71",
        "maxHP":40,
        "moveCost":5,
        "unique":1,
        "monsterClass":"humanoid",
        "movementAggressionType":"helpOthers",
        "attackDamage":{
            "min":1,
            "max":6
        },
        "spawnGroup":"stoutford_guard_camp",
        "faction":"stoutford_guard_camp",
        "phraseID":"stoutford_guard_camp2_10",
        "attackCost":5,
        "attackChance":50,
        "blockChance":100
    },
    {
        "id":"stoutford_commander",
        "name":"Borlag",
        "iconID":"monsters_ld1:41",
        "spawnGroup":"stoutford_commander",
        "phraseID":"stoutford_commander"
    },
    {
        "id":"stoutford_commoner5",
        "name":"Young man",
        "iconID":"monsters_ld1:14",
        "spawnGroup":"stoutford_commoner5",
        "phraseID":"stoutford_commoner5"
    },
    {
        "id":"berbane",
        "name":"Lord Berbane",
        "iconID":"monsters_tometik2:42",
        "spawnGroup":"berbane",
        "phraseID":"berbane"
    },
    {
        "id":"stoutford_alchemist2",
        "name":"Blornvale",
        "iconID":"monsters_rltiles1:70",
        "monsterClass":"humanoid",
        "spawnGroup":"stoutford_alchemist2",
        "phraseID":"blornvale_select_0",
        "droplistID":"stoutford_alchemist2"
    },
    {
        "id":"stoutford_old_woman",
        "name":"Croaklear",
        "iconID":"monsters_men:2",
        "spawnGroup":"stoutford_old_woman",
        "phraseID":"stoutford_old_woman"
    },
    {
        "id":"stn_burhczyd1",
        "name":"Burhczyd",
        "iconID":"monsters_ld2:8",
        "unique":1,
        "monsterClass":"humanoid",
        "phraseID":"stn_burhczyd1"
    },
    {
        "id":"stn_burhczyd2",
        "name":"Burhczyd",
        "iconID":"monsters_ld2:8",
        "unique":1,
        "monsterClass":"humanoid",
        "phraseID":"stn_burhczyd2"
    },
    {
        "id":"stn_burhczyd3",
        "name":"Burhczyd",
        "iconID":"monsters_ld2:8",
        "unique":1,
        "monsterClass":"humanoid",
        "phraseID":"stn_burhczyd3"
    },
    {
        "id":"stn_burhczyd4",
        "name":"Burhczyd",
        "iconID":"monsters_ld2:8",
        "unique":1,
        "monsterClass":"humanoid",
        "phraseID":"stn_burhczyd4"
    },
    {
        "id":"stn_burhczyd5",
        "name":"Burhczyd",
        "iconID":"monsters_ld2:8",
        "unique":1,
        "monsterClass":"humanoid",
        "phraseID":"stn_burhczyd4"
    },
    {
        "id":"stn_burhczyd6",
        "name":"Burhczyd",
        "iconID":"monsters_ld2:8",
        "unique":1,
        "monsterClass":"humanoid",
        "phraseID":"stn_burhczyd4"
    },
    {
        "id":"stn_burhczyd7",
        "name":"Burhczyd",
        "iconID":"monsters_ld2:8",
        "unique":1,
        "monsterClass":"humanoid",
        "phraseID":"stn_burhczyd4"
    },
    {
        "id":"stn_burhczyd8",
        "name":"Burhczyd",
        "iconID":"monsters_ld2:8",
        "unique":1,
        "monsterClass":"humanoid",
        "phraseID":"stn_burhczyd4"
    },
    {
        "id":"stn_burhczyd9",
        "name":"Burhczyd",
        "iconID":"monsters_ld2:8",
        "unique":1,
        "monsterClass":"humanoid",
        "phraseID":"stn_burhczyd4"
    },
    {
        "id":"stn_gyra",
        "name":"Gyra",
        "iconID":"monsters_ld1:158",
        "unique":1,
        "monsterClass":"humanoid",
        "phraseID":"stn_gyra_init"
    },
    {
        "id":"stn_gyra1",
        "name":"Gyra",
        "iconID":"monsters_ld1:158",
        "moveCost":2,
        "unique":1,
        "monsterClass":"humanoid",
        "movementAggressionType":"wholeMap",
        "phraseID":"stn_gyra"
    },
    {
        "id":"stn_gyra2",
        "name":"Gyra",
        "iconID":"monsters_ld1:158",
        "moveCost":2,
        "unique":1,
        "monsterClass":"humanoid",
        "movementAggressionType":"wholeMap",
        "phraseID":"stn_gyra"
    },
    {
        "id":"stn_gyra3",
        "name":"Gyra",
        "iconID":"monsters_ld1:158",
        "moveCost":2,
        "unique":1,
        "monsterClass":"humanoid",
        "movementAggressionType":"wholeMap",
        "phraseID":"stn_gyra"
    },
    {
        "id":"stn_gyra4",
        "name":"Gyra",
        "iconID":"monsters_ld1:158",
        "moveCost":2,
        "unique":1,
        "monsterClass":"humanoid",
        "movementAggressionType":"wholeMap",
        "phraseID":"stn_gyra"
    },
    {
        "id":"stn_gyra5",
        "name":"Gyra",
        "iconID":"monsters_ld1:158",
        "moveCost":2,
        "unique":1,
        "monsterClass":"humanoid",
        "movementAggressionType":"wholeMap",
        "phraseID":"stn_gyra"
    },
    {
        "id":"stn_gyra6",
        "name":"Gyra",
        "iconID":"monsters_ld1:158",
        "moveCost":2,
        "unique":1,
        "monsterClass":"humanoid",
        "movementAggressionType":"wholeMap",
        "phraseID":"stn_gyra"
    },
    {
        "id":"stn_gyra7",
        "name":"Gyra",
        "iconID":"monsters_ld1:158",
        "moveCost":2,
        "unique":1,
        "monsterClass":"humanoid",
        "movementAggressionType":"wholeMap",
        "phraseID":"stn_gyra"
    },
    {
        "id":"stn_gyra8",
        "name":"Gyra",
        "iconID":"monsters_ld1:158",
        "moveCost":2,
        "unique":1,
        "monsterClass":"humanoid",
        "movementAggressionType":"wholeMap",
        "phraseID":"stn_gyra"
    },
    {
        "id":"stn_gyra9",
        "name":"Gyra",
        "iconID":"monsters_ld1:158",
        "moveCost":2,
        "unique":1,
        "monsterClass":"humanoid",
        "movementAggressionType":"wholeMap",
        "phraseID":"stn_gyra"
    },
    {
        "id":"stn_gyraA",
        "name":"Gyra",
        "iconID":"monsters_ld1:158",
        "moveCost":2,
        "unique":1,
        "monsterClass":"humanoid",
        "movementAggressionType":"wholeMap",
        "phraseID":"stn_gyra"
    },
    {
        "id":"stn_gyraB",
        "name":"Gyra",
        "iconID":"monsters_ld1:158",
        "moveCost":2,
        "unique":1,
        "monsterClass":"humanoid",
        "movementAggressionType":"wholeMap",
        "phraseID":"stn_gyra"
    },
    {
        "id":"stn_gyraC",
        "name":"Gyra",
        "iconID":"monsters_ld1:158",
        "moveCost":2,
        "unique":1,
        "monsterClass":"humanoid",
        "movementAggressionType":"wholeMap",
        "phraseID":"stn_gyra"
    },
    {
        "id":"stn_colonel",
        "name":"Colonel Lutarc",
        "iconID":"monsters_rltiles2:37",
        "unique":1,
        "monsterClass":"humanoid",
        "phraseID":"stn_colonel_30"
    },
    {
        "id":"stn_colonel_mons1",
        "name":"Lizard",
        "iconID":"monsters_tometik2:12",
        "maxHP":100,
        "maxAP":10,
        "moveCost":5,
        "unique":1,
        "monsterClass":"humanoid",
        "movementAggressionType":"protectSpawn",
        "attackDamage":{
            "min":1,
            "max":4
        },
        "attackCost":4,
        "attackChance":40,
        "blockChance":120,
        "damageResistance":5
    },
    {
        "id":"stn_colonel_mons2",
        "name":"Skeleton",
        "iconID":"monsters_rltiles2:177",
        "maxHP":100,
        "maxAP":10,
        "moveCost":5,
        "unique":1,
        "monsterClass":"construct",
        "movementAggressionType":"protectSpawn",
        "attackDamage":{
            "min":1,
            "max":4
        },
        "attackCost":4,
        "attackChance":40,
        "blockChance":120,
        "damageResistance":5
    },
    {
        "id":"stn_colonel_mons3",
        "name":"Mikhail",
        "iconID":"monsters_mage2:0",
        "maxHP":100,
        "maxAP":10,
        "moveCost":5,
        "unique":1,
        "monsterClass":"humanoid",
        "movementAggressionType":"protectSpawn",
        "attackDamage":{
            "min":1,
            "max":4
        },
        "attackCost":4,
        "attackChance":40,
        "blockChance":120,
        "damageResistance":5
    },
    {
        "id":"stn_colonel_mons3b",
        "name":"Mikhail",
        "iconID":"monsters_mage2:0",
        "maxHP":100,
        "maxAP":10,
        "moveCost":5,
        "unique":1,
        "monsterClass":"humanoid",
        "movementAggressionType":"protectSpawn",
        "attackDamage":{
            "min":1,
            "max":4
        },
        "attackCost":4,
        "attackChance":40,
        "blockChance":120,
        "damageResistance":5
    },
    {
        "id":"stn_colonel_mons4",
        "name":"Giant serpent",
        "iconID":"monsters_rltiles2:22",
        "maxHP":100,
        "maxAP":10,
        "moveCost":5,
        "unique":1,
        "monsterClass":"reptile",
        "movementAggressionType":"protectSpawn",
        "attackDamage":{
            "min":1,
            "max":4
        },
        "attackCost":4,
        "attackChance":40,
        "blockChance":120,
        "damageResistance":5
    },
    {
        "id":"stn_colonel_mons5",
        "name":"Bully",
        "iconID":"monsters_ld2:119",
        "maxHP":100,
        "maxAP":10,
        "moveCost":10,
        "unique":1,
        "monsterClass":"humanoid",
        "movementAggressionType":"protectSpawn",
        "attackDamage":{
            "min":5,
            "max":10
        },
        "attackCost":6,
        "attackChance":60,
        "blockChance":120,
        "damageResistance":8
    },
    {
        "id":"stn_lizard",
        "name":"Lizard",
        "iconID":"monsters_tometik2:12",
        "maxHP":50,
        "maxAP":10,
        "moveCost":3,
        "unique":1,
        "monsterClass":"reptile",
        "movementAggressionType":"protectSpawn",
        "attackDamage":{
            "min":4,
            "max":7
        },
        "attackCost":4,
        "attackChance":40,
        "blockChance":120,
        "damageResistance":5
    },
    {
        "id":"stn_boralla",
        "name":"Boralla",
        "iconID":"monsters_tometik2:54",
        "unique":0,
        "monsterClass":"humanoid",
        "spawnGroup":"stn_boralla",
        "phraseID":"stn_boralla"
    },
    {
        "id":"stn_boralla1",
        "name":"Boralla",
        "iconID":"monsters_tometik2:54",
        "unique":1,
        "monsterClass":"humanoid",
        "spawnGroup":"stn_boralla1",
        "phraseID":"stn_boralla1"
    },
    {
        "id":"stn_boralla2",
        "name":"Boralla",
        "iconID":"monsters_tometik2:54",
        "unique":1,
        "monsterClass":"humanoid",
        "spawnGroup":"stn_boralla2",
        "phraseID":"stn_boralla2"
    },
    {
        "id":"stn_boralla3",
        "name":"Boralla",
        "iconID":"monsters_tometik2:54",
        "unique":1,
        "monsterClass":"humanoid",
        "spawnGroup":"stn_boralla3",
        "phraseID":"stn_boralla3"
    },
    {
        "id":"stn_boralla4",
        "name":"Boralla",
        "iconID":"monsters_tometik2:54",
        "unique":1,
        "monsterClass":"humanoid",
        "spawnGroup":"stn_boralla4",
        "phraseID":"stn_boralla4"
    },
    {
        "id":"stn_boralla5",
        "name":"Boralla",
        "iconID":"monsters_tometik2:54",
        "unique":1,
        "monsterClass":"humanoid",
        "spawnGroup":"stn_boralla5",
        "phraseID":"stn_boralla5"
    },
    {
        "id":"stn_boralla6",
        "name":"Boralla",
        "iconID":"monsters_tometik2:54",
        "unique":1,
        "monsterClass":"humanoid",
        "spawnGroup":"stn_boralla6",
        "phraseID":"stn_boralla6"
    },
    {
        "id":"stn_boralla7",
        "name":"Boralla",
        "iconID":"monsters_tometik2:54",
        "unique":1,
        "monsterClass":"humanoid",
        "spawnGroup":"stn_boralla7",
        "phraseID":"stn_boralla7"
    },
    {
        "id":"stn_horse",
        "name":"Horse",
        "iconID":"monsters_ld2:66",
        "monsterClass":"animal",
        "phraseID":"stn_horse"
    },
    {
        "id":"blornvale_wolf",
        "name":"Great dark wolf",
        "iconID":"monsters_rltiles2:109",
        "maxHP":30,
        "unique":1,
        "monsterClass":"animal",
        "attackDamage":{
            "min":1,
            "max":3
        },
        "spawnGroup":"blornvale_wolf",
        "attackCost":5,
        "attackChance":50,
        "blockChance":20
    },
    {
        "id":"none",
        "name":"Dummy NPC",
        "iconID":"monsters_guynmart:8"
    },
    {
        "id":"erwyn_skel_lute",
        "name":"Lutenist",
        "iconID":"monsters_fatboy73:41",
        "monsterClass":"undead",
        "spawnGroup":"erwyn_skel_lute",
        "phraseID":"erwyn_skel_band"
    },
    {
        "id":"erwyn_skel_hornet",
        "name":"Horn player",
        "iconID":"monsters_fatboy73:43",
        "monsterClass":"undead",
        "spawnGroup":"erwyn_skel_hornet",
        "phraseID":"erwyn_skel_band"
    },
    {
        "id":"erwyn_skel_drum",
        "name":"Drummer",
        "iconID":"monsters_fatboy73:45",
        "monsterClass":"undead",
        "spawnGroup":"erwyn_skel_drum",
        "phraseID":"erwyn_skel_band"
    },
    {
        "id":"erwyn_skel_cymbal",
        "name":"Cymbalist",
        "iconID":"monsters_fatboy73:47",
        "monsterClass":"undead",
        "spawnGroup":"erwyn_skel_cymbal",
        "phraseID":"erwyn_skel_band"
    },
    {
        "id":"cave_troll_7",
        "name":"Cave troll",
        "iconID":"monsters_tometik5:14",
        "maxHP":230,
        "maxAP":10,
        "moveCost":5,
        "unique":1,
        "monsterClass":"giant",
        "attackDamage":{
            "min":1,
            "max":15
        },
        "spawnGroup":"cave_troll_7",
        "droplistID":"cave_troll_1",
        "attackCost":5,
        "attackChance":60,
        "blockChance":40,
        "hitEffect":{
            "conditionsTarget":[
                {
                    "condition":"stunned",
                    "magnitude":1,
                    "duration":2,
                    "chance":"10"
                }
            ]
        }
    }
]